rsalette.py
asn1lette.py
rsalette-0.4.2.dist-info/METADATA
rsalette-0.4.2.dist-info/WHEEL
rsalette-0.4.2.dist-info/RECORD