Metadata-Version: 2.0
Name: rsalette
Version: 0.4.2
Home-Page: http://bitbucket.org/dholth/rsalette/
Author: Daniel Holth
Author-email: dholth@fastmail.fm
License: ASL 2
Keywords: rsa jwk jwt
Platform: UNKNOWN
Classifier: Topic :: Security :: Cryptography
Classifier: License :: OSI Approved :: Apache Software License
Provides-Extra: test
Requires-Dist: coverage; extra == 'test'
Requires-Dist: nose; extra == 'test'
